LICENSE
MANIFEST.in
README.md
setup.py
foster/__init__.py
foster/build.py
foster/command.py
foster/init.py
foster/main.py
foster/publish.py
foster/test.py
foster/utils.py
foster.egg-info/PKG-INFO
foster.egg-info/SOURCES.txt
foster.egg-info/dependency_links.txt
foster.egg-info/entry_points.txt
foster.egg-info/requires.txt
foster.egg-info/top_level.txt
foster/samples/package.py
foster/samples/pypirc
foster/samples/setup.py