Metadata-Version: 1.0
Name: foster
Version: 0.1.0
Summary: An easy way to publish your python packages
Home-page: https://github.com/hugollm/foster
Author: Hugo Leonardo Leão Mota
Author-email: hugo.txt@gmail.com
License: MIT
Keywords: foster python package build publish
Platform: UNKNOWN
